egse/gui/__init__.py
egse/gui/buttons.py
egse/gui/led.py
egse/gui/limitswitch.py
egse/gui/states.py
egse/gui/styles.qss
egse/gui/switch.py
egse/gui/icons/aeu-cs-start.svg
egse/gui/icons/aeu-cs-stop.svg
egse/gui/icons/aeu-cs.svg
egse/gui/icons/aeu_cs-started.svg
egse/gui/icons/aeu_cs-stopped.svg
egse/gui/icons/aeu_cs.svg
egse/gui/icons/alert.svg
egse/gui/icons/arrow-double-left.png
egse/gui/icons/arrow-double-right.png
egse/gui/icons/arrow-up.svg
egse/gui/icons/backward.svg
egse/gui/icons/busy.svg
egse/gui/icons/cleaning.svg
egse/gui/icons/color-scheme.svg
egse/gui/icons/cs-connected-alert.svg
egse/gui/icons/cs-connected-disabled.svg
egse/gui/icons/cs-connected.svg
egse/gui/icons/cs-not-connected.svg
egse/gui/icons/double-left-arrow.svg
egse/gui/icons/double-right-arrow.svg
egse/gui/icons/erase-disabled.svg
egse/gui/icons/erase.svg
egse/gui/icons/fitsgen-start.svg
egse/gui/icons/fitsgen-stop.svg
egse/gui/icons/fitsgen.svg
egse/gui/icons/forward.svg
egse/gui/icons/fov-hk-start.svg
egse/gui/icons/fov-hk-stop.svg
egse/gui/icons/fov-hk.svg
egse/gui/icons/front-desk.svg
egse/gui/icons/home-actioned.svg
egse/gui/icons/home-disabled.svg
egse/gui/icons/home.svg
egse/gui/icons/info.svg
egse/gui/icons/invalid.png
egse/gui/icons/led-green.svg
egse/gui/icons/led-grey.svg
egse/gui/icons/led-orange.svg
egse/gui/icons/led-red.svg
egse/gui/icons/led-square-green.svg
egse/gui/icons/led-square-grey.svg
egse/gui/icons/led-square-orange.svg
egse/gui/icons/led-square-red.svg
egse/gui/icons/limit-switch-all-green.svg
egse/gui/icons/limit-switch-all-red.svg
egse/gui/icons/limit-switch-el+.svg
egse/gui/icons/limit-switch-el-.svg
egse/gui/icons/location-marker.svg
egse/gui/icons/logo-dpu.svg
egse/gui/icons/logo-gimbal.svg
egse/gui/icons/logo-huber.svg
egse/gui/icons/logo-ogse.svg
egse/gui/icons/logo-puna.svg
egse/gui/icons/logo-tcs.svg
egse/gui/icons/logo-zonda.svg
egse/gui/icons/maximize.svg
egse/gui/icons/meter.svg
egse/gui/icons/more.svg
egse/gui/icons/n-fee-hk-start.svg
cgse_gui-2025.0.9.dist-info/METADATA
cgse_gui-2025.0.9.dist-info/WHEEL
cgse_gui-2025.0.9.dist-info/entry_points.txt
cgse_gui-2025.0.9.dist-info/RECORD
