Metadata-Version: 2.4
Name: cgse-gui
Version: 2025.0.9
Summary: GUI components for CGSE
Author-email: Rik Huygen <rik.huygen@kuleuven.be>, Sara Regibo <sara.regibo@kuleuven.be>
License-Expression: MIT
Keywords: CGSE,Common-EGSE,GUI
Requires-Python: >=3.9
Requires-Dist: cgse-common
Requires-Dist: pyqt5>=5.15.11
